{"type":"Topology","objects":{"states":{"type":"GeometryCollection","geometries":[{"type":"Polygon","properties":{"name":"Serravalle"},"id":"SM-09","arcs":[[0,1,2]]},{"type":"Polygon","properties":{"name":"Domagnano"},"id":"SM-03","arcs":[[3,4,5,-1]]},{"type":"Polygon","properties":{"name":"Faetano"},"id":"SM-04","arcs":[[6,7,8,9,-5]]},{"type":"Polygon","properties":{"name":"Montegiardino"},"id":"SM-08","arcs":[[10,11,-8]]},{"type":"Polygon","properties":{"name":"Fiorentino"},"id":"SM-05","arcs":[[12,13,14,15,-9,-12]]},{"type":"Polygon","properties":{"name":"Chiesanuova"},"id":"SM-02","arcs":[[16,17,-14]]},{"type":"Polygon","properties":{"name":"San Marino"},"id":"SM-07","arcs":[[18,19,20,-15,-18]]},{"type":"Polygon","properties":{"name":"Acquaviva"},"id":"SM-01","arcs":[[21,22,-20]]},{"type":"Polygon","properties":{"name":"Borgo Maggiore"},"id":"SM-06","arcs":[[23,-2,-6,-10,-16,-21,-23]]}]}},"arcs":[[[9925,8063],[-1685,-580],[-790,-864],[-738,924],[-815,-626]],[[5897,6917],[-357,1460],[-1610,166]],[[3930,8543],[2463,1068],[2723,388],[809,-1936]],[[9925,8063],[74,-1761]],[[9999,6302],[-3236,-1739]],[[6763,4563],[-1172,775],[306,1579]],[[9999,6302],[-1274,-2860]],[[8725,3442],[-944,-70]],[[7781,3372],[-331,208]],[[7450,3580],[178,686],[-865,297]],[[8725,3442],[-1287,-2556]],[[7438,886],[343,2486]],[[7438,886],[-372,-532],[-1812,-219]],[[5254,135],[-580,1181]],[[4674,1316],[560,1162]],[[5234,2478],[1554,328],[662,774]],[[5254,135],[-1116,-135],[-2820,1233],[-909,1623]],[[409,2856],[1795,-80],[1171,-447],[484,-1013],[815,0]],[[409,2856],[-409,732]],[[0,3588],[2713,737],[357,1043]],[[3070,5368],[1757,-1400],[407,-1490]],[[0,3588],[947,2637],[1975,1689]],[[2922,7914],[937,-1384],[-764,-149],[-25,-1013]],[[2922,7914],[1008,629]]],"transform":{"scale":[0.000010589785047408494,0.000009052032303237829],"translate":[12.385628745000105,43.892055515]}}